{"cameraMode":{"drawMode":0,"name":"Shaded","section":"Shading Mode"},"sceneLighting":true,"audioPlay":false,"sceneViewState":{"m_AlwaysRefresh":false,"showFog":true,"showSkybox":true,"showFlares":true,"showImageEffects":true,"showParticleSystems":true,"showVisualEffectGraphs":true,"m_FxEnabled":true},"in2DMode":false,"pivot":{"x":3.0946197509765627,"y":2.614243507385254,"z":-1.637742042541504},"rotation":{"x":0.19564956426620484,"y":-0.5188429951667786,"z":0.12334524095058441,"w":0.8229886293411255},"size":3.77705454826355,"orthographic":false}